ppdland/__init__.py
ppdland/data.py
ppdland/entities.py
ppdland/scenarios.py
ppdland/__pycache__/__init__.cpython-311.pyc
ppdland/__pycache__/data.cpython-311.pyc
ppdland/__pycache__/entities.cpython-311.pyc
ppdland/__pycache__/scenarios.cpython-311.pyc
ppdland/parameters/__init__.py
ppdland/parameters/lump_sum_transfer.yaml
ppdland/parameters/tax_scale.yaml
ppdland/variables/__init__.py
ppdland/variables/variables.py
ppdland/variables/__pycache__/__init__.cpython-311.pyc
ppdland/variables/__pycache__/variables.cpython-311.pyc
OpenFisca_PPDLand-0.4.0.dist-info/METADATA
OpenFisca_PPDLand-0.4.0.dist-info/WHEEL
OpenFisca_PPDLand-0.4.0.dist-info/top_level.txt
OpenFisca_PPDLand-0.4.0.dist-info/RECORD
