Metadata-Version: 2.2
Name: OpenFisca-PPDLand
Version: 0.4.0
Summary: OpenFisca tax and benefit system for PPDLand
Home-page: https://github.com/openfisca/country-template
Author: Sylvain Duchesne
Author-email: sylvain.duchesne@ipp.eu
License: http://www.fsf.org/licensing/licenses/agpl-3.0.html
Keywords: benefit microsimulation social tax
Classifier: Development Status :: 3 - Alpha
Classifier: License :: OSI Approved :: GNU Affero General Public License v3
Classifier: Operating System :: POSIX
Classifier: Programming Language :: Python
Classifier: Topic :: Scientific/Engineering :: Information Analysis
Requires-Dist: OpenFisca-Core<44,>=43
Requires-Dist: OpenFisca-Survey-Manager<4.0,>=3
Requires-Dist: matplotlib
Requires-Dist: scipy
Dynamic: author
Dynamic: author-email
Dynamic: classifier
Dynamic: home-page
Dynamic: keywords
Dynamic: license
Dynamic: requires-dist
Dynamic: summary
